qctma.py
rw_cdb.py
gauss_integ/__init__.py
gauss_integ/ndim/__about__.py
gauss_integ/ndim/__init__.py
gauss_integ/ndim/enr.py
gauss_integ/ndim/enr2.py
gauss_integ/ndim/nball.py
gauss_integ/ndim/ncube.py
gauss_integ/ndim/nsimplex.py
gauss_integ/ndim/nsphere.py
gauss_integ/orthopy/__init__.py
gauss_integ/orthopy/helpers.py
gauss_integ/orthopy/c1/__init__.py
gauss_integ/orthopy/c1/associated_legendre.py
gauss_integ/orthopy/c1/chebyshev1.py
gauss_integ/orthopy/c1/chebyshev2.py
gauss_integ/orthopy/c1/gegenbauer.py
gauss_integ/orthopy/c1/jacobi.py
gauss_integ/orthopy/c1/legendre.py
gauss_integ/orthopy/c1/tools.py
gauss_integ/orthopy/cn/__init__.py
gauss_integ/orthopy/cn/main.py
gauss_integ/orthopy/cn/tools.py
gauss_integ/orthopy/e1r/__init__.py
gauss_integ/orthopy/e1r/main.py
gauss_integ/orthopy/e1r/tools.py
gauss_integ/orthopy/e1r2/__init__.py
gauss_integ/orthopy/e1r2/main.py
gauss_integ/orthopy/e1r2/tools.py
gauss_integ/orthopy/enr2/__init__.py
gauss_integ/orthopy/enr2/main.py
gauss_integ/orthopy/enr2/tools.py
gauss_integ/orthopy/s2/__init__.py
gauss_integ/orthopy/s2/tools.py
gauss_integ/orthopy/s2/xu.py
gauss_integ/orthopy/s2/zernike.py
gauss_integ/orthopy/s2/zernike2.py
gauss_integ/orthopy/t2/__init__.py
gauss_integ/orthopy/t2/main.py
gauss_integ/orthopy/t2/tools.py
gauss_integ/orthopy/tools/__init__.py
gauss_integ/orthopy/tools/generate_rc.py
gauss_integ/orthopy/u3/__init__.py
gauss_integ/orthopy/u3/main.py
gauss_integ/orthopy/u3/tools.py
gauss_integ/quadpy/__about__.py
gauss_integ/quadpy/__init__.py
gauss_integ/quadpy/_cli.py
gauss_integ/quadpy/_exception.py
gauss_integ/quadpy/_optimize.py
gauss_integ/quadpy/_scipy_compat.py
gauss_integ/quadpy/c1/__init__.py
gauss_integ/quadpy/c1/_adaptive.py
gauss_integ/quadpy/c1/_chebyshev_gauss.py
gauss_integ/quadpy/c1/_clenshaw_curtis.py
gauss_integ/quadpy/c1/_fejer.py
gauss_integ/quadpy/c1/_gauss_jacobi.py
gauss_integ/quadpy/c1/_gauss_kronrod.py
gauss_integ/quadpy/c1/_gauss_legendre.py
gauss_integ/quadpy/c1/_gauss_lobatto.py
qctma-1.0.28.dist-info/METADATA
qctma-1.0.28.dist-info/WHEEL
qctma-1.0.28.dist-info/top_level.txt
qctma-1.0.28.dist-info/RECORD
